[
  {
    "id": 1,
    "name": "Google Summer of Code (GSoC)",
    "slug": "gsoc",
    "difficulty": "intermediate",
    "program_type": "Internship",
    "timeline": "Applications Feb–Apr, coding May–Aug (varies by year)",
    "opens_in": "March",
    "deadline": "April 2, 2025",
    "description": "Work with open source organizations on a 3-month programming project during your summer break.",
    "official_site": "https://summerofcode.withgoogles.com/",
    "tags": [
      "Paid",
      "Remote",
      "Global"
    ]
  },
  {
    "id": 3,
    "name": "GirlScript Summer of Code (GSSoC)",
    "slug": "gssoc",
    "difficulty": "beginner",
    "program_type": "Open Source",
    "timeline": "Summer (often Mar–May for contributions)",
    "opens_in": "March",
    "deadline": "Varies yearly",
    "description": "Summer-long open-source program aimed at helping beginners start contributing to real projects.",
    "official_site": "https://gssoc.girlscript.tech/",
    "tags": [
      "Remote",
      "Global"
    ]
  },
  {
    "id": 4,
    "name": "Hacktoberfest",
    "slug": "hacktoberfest",
    "difficulty": "intermediate",
    "program_type": "Open Source",
    "timeline": "October 1–31 every year",
    "opens_in": "October",
    "deadline": "October 31",
    "description": "Month-long celebration of open source focused on submitting pull requests to participating repositories.",
    "official_site": "https://hacktoberfest.com/",
    "tags": [
      "Remote",
      "Global"
    ]
  },
  {
    "id": 6,
    "name": "Outreachy",
    "slug": "outreachy",
    "difficulty": "beginner",
    "program_type": "Internship",
    "timeline": "Applications typically open in January and August",
    "opens_in": "January",
    "deadline": "February 6, 2025",
    "description": "Provides internships to work in open source and open science. Internships are open to applicants around the world.",
    "official_site": "https://www.outreachy.org/",
    "tags": [
      "Paid",
      "Diversity",
      "Remote"
    ]
  },
  {
    "id": 7,
    "name": "Google Season of Docs",
    "slug": "gsod",
    "difficulty": "intermediate",
    "program_type": "Documentation",
    "timeline": "Applications typically open in March",
    "opens_in": "March",
    "deadline": "Varies yearly",
    "description": "Brings technical writers and open source projects together to improve project documentation.",
    "official_site": "https://developers.google.com/season-of-docs",
    "tags": [
      "Paid",
      "Remote",
      "Global"
    ]
  },
  {
    "id": 8,
    "name": "Linux Foundation Mentorship Program",
    "slug": "lf-mentorship",
    "difficulty": "intermediate",
    "program_type": "Internship",
    "timeline": "Multiple cohorts throughout the year",
    "opens_in": "Varies",
    "deadline": "Varies",
    "description": "Provides mentorship opportunities to work on Linux Foundation projects and gain real-world experience.",
    "official_site": "https://mentorship.lfx.linuxfoundation.org/",
    "tags": [
      "Paid",
      "Remote",
      "Global"
    ]
  }
]